axiomatic_mcp/__init__.py
axiomatic_mcp/__main__.py
axiomatic_mcp/config/config.py
axiomatic_mcp/providers/middleware_provider.py
axiomatic_mcp/providers/toolset_provider.py
axiomatic_mcp/servers/__init__.py
axiomatic_mcp/servers/annotations/__init__.py
axiomatic_mcp/servers/annotations/__main__.py
axiomatic_mcp/servers/annotations/server.py
axiomatic_mcp/servers/axmodelfitter/__init__.py
axiomatic_mcp/servers/axmodelfitter/__main__.py
axiomatic_mcp/servers/axmodelfitter/data_file_utils.py
axiomatic_mcp/servers/axmodelfitter/server.py
axiomatic_mcp/servers/documents/__init__.py
axiomatic_mcp/servers/documents/__main__.py
axiomatic_mcp/servers/documents/server.py
axiomatic_mcp/servers/equations/__init__.py
axiomatic_mcp/servers/equations/__main__.py
axiomatic_mcp/servers/equations/server.py
axiomatic_mcp/servers/pic/__init__.py
axiomatic_mcp/servers/pic/__main__.py
axiomatic_mcp/servers/pic/server.py
axiomatic_mcp/servers/pic/models/__init__.py
axiomatic_mcp/servers/pic/services/__init__.py
axiomatic_mcp/servers/pic/services/circuit_service.py
axiomatic_mcp/servers/pic/services/notebook_service.py
axiomatic_mcp/servers/pic/services/optimization_service.py
axiomatic_mcp/servers/pic/services/pdk_service.py
axiomatic_mcp/servers/pic/services/simulation_service.py
axiomatic_mcp/servers/pic/services/statements_service.py
axiomatic_mcp/servers/pic/utils/pdk.py
axiomatic_mcp/servers/pic/utils/physics.py
axiomatic_mcp/servers/pic/utils/wavelengths.py
axiomatic_mcp/servers/plots/__init__.py
axiomatic_mcp/servers/plots/__main__.py
axiomatic_mcp/servers/plots/server.py
axiomatic_mcp/shared/__init__.py
axiomatic_mcp/shared/api_client.py
axiomatic_mcp/shared/tools.py
axiomatic_mcp/shared/constants/__init__.py
axiomatic_mcp/shared/constants/api_constants.py
axiomatic_mcp/shared/documents/pdf_to_markdown.py
axiomatic_mcp/shared/models/singleton_base.py
axiomatic_mcp/shared/utils/get_unique_filename.py
axiomatic_mcp/shared/utils/prompt_utils.py
axiomatic_mcp-0.1.15.dist-info/licenses/LICENSE
axiomatic_mcp-0.1.15.dist-info/METADATA
axiomatic_mcp-0.1.15.dist-info/WHEEL
axiomatic_mcp-0.1.15.dist-info/entry_points.txt
axiomatic_mcp-0.1.15.dist-info/top_level.txt
axiomatic_mcp-0.1.15.dist-info/RECORD
