Metadata-Version: 2.4
Name: axiomatic-mcp
Version: 0.1.15
Summary: Modular MCP servers for Axiomatic_AI
Author-email: Axiomatic Team <developers@axiomatic-ai.com>
License: MIT
Project-URL: Homepage, https://github.com/Axiomatic-AI/ax-mcp
Project-URL: Issues, https://github.com/Axiomatic-AI/ax-mcp/issues
Keywords: mcp,axiomatic,ai,fastmcp
Classifier: Development Status :: 4 - Beta
Classifier: Intended Audience :: Developers
Classifier: License :: OSI Approved :: MIT License
Classifier: Programming Language :: Python :: 3
Classifier: Programming Language :: Python :: 3.11
Classifier: Programming Language :: Python :: 3.12
Classifier: Topic :: Software Development :: Libraries :: Python Modules
Requires-Python: >=3.11
License-File: LICENSE
Requires-Dist: fastmcp==2.11.3
Requires-Dist: httpx>=0.25.0
Requires-Dist: numpy>=1.21.0
Requires-Dist: pandas>=1.3.0
Requires-Dist: pydantic>=2.0.0
Requires-Dist: python-dotenv>=1.0.0
Requires-Dist: scikit-learn>=1.0.0
Requires-Dist: filetype>=1.2.0
Provides-Extra: dev
Requires-Dist: black>=23.0.0; extra == "dev"
Requires-Dist: debugpy>=1.8.0; extra == "dev"
Requires-Dist: mypy>=1.0.0; extra == "dev"
Requires-Dist: pytest>=7.0.0; extra == "dev"
Requires-Dist: ruff>=0.1.0; extra == "dev"
Provides-Extra: lean
Requires-Dist: leanclient==0.1.14; extra == "lean"
Provides-Extra: pic
Requires-Dist: cspdk>=1.0.1; extra == "pic"
Requires-Dist: gdsfactory==9.11.6; extra == "pic"
Requires-Dist: iklayout>=0.0.8; extra == "pic"
Requires-Dist: ipympl>=0.9.7; extra == "pic"
Requires-Dist: kfactory>=1.7.3; extra == "pic"
Requires-Dist: klayout>=0.30.2; extra == "pic"
Requires-Dist: klujax>=0.4.3; extra == "pic"
Requires-Dist: nbformat>=5.10.4; extra == "pic"
Requires-Dist: numpy>=1.21.0; extra == "pic"
Requires-Dist: pandas>=1.3.0; extra == "pic"
Requires-Dist: plotly>=6.1.2; extra == "pic"
Requires-Dist: sax>=0.14.5; extra == "pic"
Requires-Dist: scikit-learn>=1.0.0; extra == "pic"
Provides-Extra: all
Requires-Dist: leanclient==0.1.14; extra == "all"
Requires-Dist: cspdk>=1.0.1; extra == "all"
Requires-Dist: gdsfactory==9.11.6; extra == "all"
Requires-Dist: iklayout>=0.0.8; extra == "all"
Requires-Dist: ipympl>=0.9.7; extra == "all"
Requires-Dist: kfactory>=1.7.3; extra == "all"
Requires-Dist: klayout>=0.30.2; extra == "all"
Requires-Dist: klujax>=0.4.3; extra == "all"
Requires-Dist: nbformat>=5.10.4; extra == "all"
Requires-Dist: numpy>=1.21.0; extra == "all"
Requires-Dist: pandas>=1.3.0; extra == "all"
Requires-Dist: plotly>=6.1.2; extra == "all"
Requires-Dist: sax>=0.14.5; extra == "all"
Requires-Dist: scikit-learn>=1.0.0; extra == "all"
Dynamic: license-file
